loongdata/__init__.py
loongdata/cli.py
loongdata/download/__init__.py
loongdata/download/client.py
loongdata/download/download.py
loongdata/download/stream.py
loongdata-0.1.9.dist-info/METADATA
loongdata-0.1.9.dist-info/WHEEL
loongdata-0.1.9.dist-info/entry_points.txt
loongdata-0.1.9.dist-info/top_level.txt
loongdata-0.1.9.dist-info/RECORD
